{"_path":"/","_dir":"","_draft":false,"_partial":false,"_locale":"","title":"Nuxt Content","description":"This page corresponds to the / route of your website. You can delete it or create another file in the content/ directory.","body":{"type":"root","children":[{"type":"element","tag":"h1","props":{"id":"nuxt-content"},"children":[{"type":"text","value":"Nuxt Content"}]},{"type":"element","tag":"p","props":{},"children":[{"type":"text","value":"This page corresponds to the "},{"type":"element","tag":"code","props":{"className":[]},"children":[{"type":"text","value":"/"}]},{"type":"text","value":" route of your website. You can delete it or create another file in the "},{"type":"element","tag":"code","props":{"className":[]},"children":[{"type":"text","value":"content/"}]},{"type":"text","value":" directory."}]},{"type":"element","tag":"p","props":{},"children":[{"type":"text","value":"Try to navigate to "},{"type":"element","tag":"a","props":{"href":"/about"},"children":[{"type":"text","value":"/about"}]},{"type":"text","value":". These 2 pages are rendered by the "},{"type":"element","tag":"code","props":{"className":[]},"children":[{"type":"text","value":"pages/[...slug].vue"}]},{"type":"text","value":" component."}]},{"type":"element","tag":"hr","props":{},"children":[]},{"type":"element","tag":"p","props":{},"children":[{"type":"text","value":"Look at the "},{"type":"element","tag":"a","props":{"href":"https://content.nuxtjs.org/","rel":["nofollow"]},"children":[{"type":"text","value":"Content documentation"}]},{"type":"text","value":" to learn more."}]}],"toc":{"title":"","searchDepth":2,"depth":2,"links":[]}},"_type":"markdown","_id":"content:index.md","_source":"content","_file":"index.md","_extension":"md"}